Libreria_De_Cursos/__init__.py
Libreria_De_Cursos/courses.py
Libreria_De_Cursos/utils.py
buscador_de_cursos_by_jhonatanhck_hack4u-0.5.0.dist-info/METADATA
buscador_de_cursos_by_jhonatanhck_hack4u-0.5.0.dist-info/WHEEL
buscador_de_cursos_by_jhonatanhck_hack4u-0.5.0.dist-info/top_level.txt
buscador_de_cursos_by_jhonatanhck_hack4u-0.5.0.dist-info/RECORD
