Metadata-Version: 2.4
Name: Buscador_De_Cursos_by_Jhonatanhck_hack4u
Version: 0.5.0
Summary: Una biblioteca para consultar cursos de hack4u,
Home-page: https://hack4u.io
Author: Jhonatan Pimentel
Dynamic: author
Dynamic: description
Dynamic: description-content-type
Dynamic: home-page
Dynamic: summary
